Bubot_CoAP/__init__.py
Bubot_CoAP/coap_protocol.py
Bubot_CoAP/coap_tcp_protocol.py
Bubot_CoAP/coap_udp_protocol.py
Bubot_CoAP/defines.py
Bubot_CoAP/serializer.py
Bubot_CoAP/serializer_tcp.py
Bubot_CoAP/serializer_udp.py
Bubot_CoAP/server.py
Bubot_CoAP/transaction.py
Bubot_CoAP/utils.py
Bubot_CoAP/endpoint/__init__.py
Bubot_CoAP/endpoint/endpoint.py
Bubot_CoAP/endpoint/simple_server.py
Bubot_CoAP/endpoint/tcp.py
Bubot_CoAP/endpoint/udp.py
Bubot_CoAP/endpoint/udp_tls.py
Bubot_CoAP/layers/__init__.py
Bubot_CoAP/layers/block_layer.py
Bubot_CoAP/layers/cache_layer.py
Bubot_CoAP/layers/callback_layer.py
Bubot_CoAP/layers/endpoint_layer.py
Bubot_CoAP/layers/forward_layer.py
Bubot_CoAP/layers/message_layer.py
Bubot_CoAP/layers/observe_layer.py
Bubot_CoAP/layers/request_layer.py
Bubot_CoAP/layers/resource_layer.py
Bubot_CoAP/messages/__init__.py
Bubot_CoAP/messages/message.py
Bubot_CoAP/messages/option.py
Bubot_CoAP/messages/options.py
Bubot_CoAP/messages/optiontypes.py
Bubot_CoAP/messages/request.py
Bubot_CoAP/messages/response.py
Bubot_CoAP/messages/numbers/__init__.py
Bubot_CoAP/messages/numbers/codes.py
Bubot_CoAP/messages/numbers/constants.py
Bubot_CoAP/messages/numbers/optionnumbers.py
Bubot_CoAP/messages/numbers/types.py
Bubot_CoAP/resources/__init__.py
Bubot_CoAP/resources/remoteResource.py
Bubot_CoAP/resources/resource.py
Bubot_CoAP-2.0.0.dist-info/LICENSE
Bubot_CoAP-2.0.0.dist-info/METADATA
Bubot_CoAP-2.0.0.dist-info/WHEEL
Bubot_CoAP-2.0.0.dist-info/top_level.txt
Bubot_CoAP-2.0.0.dist-info/RECORD
